datadrift/__init__.py
datadrift/datadrift.py
datadrift/detect_drift.py
datadrift/parse_results.py
datadrift-0.1.1.dist-info/LICENSE
datadrift-0.1.1.dist-info/METADATA
datadrift-0.1.1.dist-info/WHEEL
datadrift-0.1.1.dist-info/top_level.txt
datadrift-0.1.1.dist-info/RECORD
