Metadata-Version: 2.1
Name: datadrift
Version: 0.1.1
Summary: Detecting data/concept drifts in new data.
Home-page: https://github.com/samsonq/datadrift
Author: Samson Qian
Author-email: samsonqian@gmail.com
License: MIT
Keywords: data-drift concept-drift
Platform: UNKNOWN
Requires-Python: >=3.6
License-File: LICENSE
